Metadata-Version: 2.1
Name: jtypes.pyjnius
Version: 1.1.4b4
Summary: Dynamic access to Java classes from Python (ctypes/cffi-based PyJNIus)
Home-page: http://pypi.python.org/pypi/jtypes.pyjnius/
Author: Adam Karpierz
Author-email: adam@karpierz.net
Maintainer: Adam Karpierz
Maintainer-email: adam@karpierz.net
License: MIT License ; http://opensource.org/licenses/MIT
Download-URL: http://pypi.python.org/pypi/jtypes.pyjnius/
Keywords: jtypes, jt, jpype, jep, pyjnius, jpy, javabridge, pyjava, jcc,,py4j, jython, java, pythonjava
Platform: any
Classifier: Development Status :: 4 - Beta
Classifier: Intended Audience :: Developers
Classifier: License :: OSI Approved :: MIT License
Classifier: Natural Language :: Polish
Classifier: Operating System :: OS Independent
Classifier: Programming Language :: Java
Classifier: Programming Language :: Python
Classifier: Programming Language :: Python :: 2
Classifier: Programming Language :: Python :: 2.7
Classifier: Programming Language :: Python :: 3
Classifier: Programming Language :: Python :: 3.4
Classifier: Programming Language :: Python :: 3.5
Classifier: Programming Language :: Python :: 3.6
Classifier: Programming Language :: Python :: 3.7
Classifier: Programming Language :: Python :: Implementation :: CPython
Classifier: Programming Language :: Python :: Implementation :: IronPython
Classifier: Programming Language :: Python :: Implementation :: PyPy
Classifier: Programming Language :: Python :: Implementation :: Stackless
Classifier: Topic :: Software Development :: Libraries :: Java Libraries
Classifier: Topic :: Software Development :: Libraries :: Python Modules
Requires-Python: >=2.7.0,!=3.0.*,!=3.1.*,!=3.2.*,!=3.3.*
Provides-Extra: doc
Provides-Extra: test
